shenaniganfs/__init__.py
shenaniganfs/client.py
shenaniganfs/fs.py
shenaniganfs/fs_manager.py
shenaniganfs/nfs2.py
shenaniganfs/nfs3.py
shenaniganfs/nfs_utils.py
shenaniganfs/portmanager.py
shenaniganfs/rpchelp.py
shenaniganfs/server.py
shenaniganfs/statd.py
shenaniganfs/transport.py
shenaniganfs/zipfs.py
shenaniganfs/generated/__init__.py
shenaniganfs/generated/rfc1094.py
shenaniganfs/generated/rfc1813.py
shenaniganfs/generated/rfc1831.py
shenaniganfs/generated/rfc1833_portmapper.py
shenaniganfs/generated/rfc1833_rpcbind.py
shenaniganfs/generated/statd.py
shenaniganfs/tools/__init__.py
shenaniganfs/tools/rpcgen.py
ShenanigaNFS-0.2.dist-info/LICENSE.md
ShenanigaNFS-0.2.dist-info/METADATA
ShenanigaNFS-0.2.dist-info/WHEEL
ShenanigaNFS-0.2.dist-info/top_level.txt
ShenanigaNFS-0.2.dist-info/RECORD
