Metadata-Version: 2.1
Name: ShenanigaNFS
Version: 0.2
Summary: Library for making somewhat conformant NFS and SunRPC clients and servers
Home-page: https://github.com/JordanMilne/ShenanigaNFS
Author: Jordan Milne
Author-email: JordanMilne@users.noreply.github.com
Classifier: Programming Language :: Python :: 3
Classifier: Programming Language :: Python :: 3.7
Classifier: Intended Audience :: Developers
Classifier: License :: OSI Approved :: MIT License
Classifier: Operating System :: OS Independent
Requires-Python: >=3.7
License-File: LICENSE.md
Provides-Extra: rpcgen
Requires-Dist: ply ~=3.11 ; extra == 'rpcgen'
